<?xml version="1.0" encoding="UTF-8"?>
<program xmlns:vc="http://www.w3.org/2007/XMLSchema-versioning"
    xmlns:xsi="http://www.w3.org/2001/XMLSchema-instance"
    xsi:schemaLocation="file:/C:/My%20Documents/GitHub/swiML ./swiML.xsd">

    <title>Continuation</title>
    <author>
        <firstName>Christoph</firstName>
        <lastName>Bartneck</lastName>
    </author>
    <programDescription>Continues test xml</programDescription>
    <poolLength>25</poolLength>
    <lengthUnit>meters</lengthUnit>
    
    
    <instruction>
        <repetition>
            <repetitionCount>4</repetitionCount>
            <length><lengthAsDistance>100</lengthAsDistance></length>
            <stroke><standardStroke>any</standardStroke></stroke>
            <rest><sinceStart>PT1M45S</sinceStart></rest>
            
            
            <instruction>
                <repetition>
                    <repetitionCount>4</repetitionCount>
                    
                    <instruction>
                        <length><lengthAsDistance>200</lengthAsDistance></length>
                        <rest><sinceStart>PT1M45S</sinceStart></rest>
                        
                    </instruction>
                </repetition>
            </instruction>
            <instruction>
                <repetition>
                    <repetitionCount>4</repetitionCount>
                    <instruction>
                        <length><lengthAsDistance>100</lengthAsDistance></length>
                        <stroke><standardStroke>any</standardStroke></stroke>
                    </instruction>
                </repetition>
            </instruction>
        </repetition>
    </instruction>
    <instruction>
        <length><lengthAsDistance>100</lengthAsDistance></length>
        <stroke><standardStroke>any</standardStroke></stroke>
        <rest><sinceStart>PT1M45S</sinceStart></rest>
        
    </instruction>

</program>
